{
  "query": "Como social se relaciona com papéis?",
  "timestamp": "2025-04-30T16:31:44.069495Z",
  "qa": [
    {
      "question": "Papéis sociais - Brasil Escola",
      "answer": "Os papéis sociais são formas de comportamento previamente estipuladas para os indivíduos de uma posição social específica. Você provavelmente já se deparou com uma situação em que as pessoas envolvidas esperavam um tipo de comportamento de sua parte tendo como base uma característica sua.",
      "url": "https://brasilescola.uol.com.br/sociologia/papeis-sociais.htm"
    },
    {
      "question": "Exemplos de papel social. - pt.uniproyecta.com",
      "answer": "Alguns exemplos de papéis sociais são o papel de pai/mãe, o papel de filho/filha, o papel de marido/esposa, o papel de amigo, o papel de irmão/irmã, etc. Cada um destes papéis sociais implica um conjunto de expectativas e responsabilidades que devem ser cumpridas.",
      "url": "https://pt.uniproyecta.com/exemplos-de-pap%C3%A9is-sociais/"
    }
  ]
}