{
  "query": "Como inovação se relaciona com américa?",
  "timestamp": "2025-04-30T14:03:15.008617Z",
  "qa": [
    {
      "question": "A América Latina E Sua Relação Com a Inovação Para a ... - Unesc",
      "answer": "Para se manter nesse ambiente e não sofrer danos, os países precisam se adequar as exigências do ambiente competitivo, melhorando a forma como empreendem e utilizando a inovação como um recurso-chave para o desenvolvimento de suas economias.",
      "url": "https://www.unesc.net/portal/blog/ver/571/39320"
    },
    {
      "question": "5 sinais de que a América Latina já entrou na era da IA",
      "answer": "A inteligência artificial se tornou pré-requisito para receber venture capital, consolidando-se como um diferencial estratégico e, cada vez mais, como uma exigência para startups que buscam investimento. Na América Latina, onde os recursos são mais escassos, os aportes estão se concentrando em empresas de IA.",
      "url": "https://startups.com.br/pesquisas/5-sinais-de-que-a-america-latina-ja-entrou-na-era-da-ia/"
    }
  ]
}